COPYING
MANIFEST.in
README.md
pyproject.toml
python-norpm.spec
norpm/__init__.py
norpm/arch.py
norpm/builtins.py
norpm/exceptions.py
norpm/expression.py
norpm/getopt.py
norpm/logging.py
norpm/lua.py
norpm/macro.py
norpm/macrofile.py
norpm/specfile.py
norpm/tokenize.py
norpm/versions.py
norpm.egg-info/PKG-INFO
norpm.egg-info/SOURCES.txt
norpm.egg-info/dependency_links.txt
norpm.egg-info/entry_points.txt
norpm.egg-info/requires.txt
norpm.egg-info/top_level.txt
norpm/cli/conditions_for_arch_statements.py
norpm/cli/expand_specfile.py
tests/test_arch.py
tests/test_arch_tracer.py
tests/test_builtins.py
tests/test_condition_context.py
tests/test_condition_parser.py
tests/test_expression.py
tests/test_full_spec_expansion.py
tests/test_macro.py
tests/test_quote_split.py
tests/test_rpmmacros.py
tests/test_shell_hacks.py
tests/test_spec_expansion.py
tests/test_spec_parser.py
tests/test_version_compare.py
tests/full_spec_expansion/2048-cli.spec
tests/full_spec_expansion/2048-cli.spec.exp
tests/full_spec_expansion/clustershell.spec
tests/full_spec_expansion/clustershell.spec.exp
tests/full_spec_expansion/nest.spec
tests/full_spec_expansion/nest.spec.exp