Metadata-Version: 2.4
Name: norpm
Version: 1.7
Summary: RPM Macro Expansion in Python
Author-email: Pavel Raiskup <pavel@raiskup.cz>
License: LGPL-2.1-or-later
Project-URL: Homepage, https://github.com/praiskup/norpm
Project-URL: Repository, https://github.com/praiskup/norpm.git
Project-URL: Issues, https://github.com/praiskup/norpm/issues
License-File: COPYING
Requires-Dist: ply
Dynamic: license-file
